asynctimer/Timer.py
asynctimer/__init__.py
async_strict_timer-0.1.0.dist-info/METADATA
async_strict_timer-0.1.0.dist-info/WHEEL
async_strict_timer-0.1.0.dist-info/top_level.txt
async_strict_timer-0.1.0.dist-info/RECORD
