Metadata-Version: 2.4
Name: async-strict-timer
Version: 0.1.0
Summary: A precise, cancellation-safe asyncio timer for Python that avoids drift
Author-email: sumitdhyani <sumitdhyani1@gmail.com>
Keywords: asyncio timer,deterministic,drift,overrun
Classifier: Programming Language :: Python :: 3
Classifier: Programming Language :: Python :: 3 :: Only
Classifier: Framework :: AsyncIO
Classifier: Intended Audience :: Developers
Classifier: Topic :: Software Development :: Libraries
Classifier: Topic :: Utilities
Requires-Python: >=3.8
